netseasy/__init__.py
netseasy/admin.py
netseasy/apps.py
netseasy/authorization.py
netseasy/credentials.py
netseasy/decorators.py
netseasy/interface.py
netseasy/urls.py
netseasy/views.py
netseasy/migrations/0001_initial.py
netseasy/migrations/0002_auto_20210616_2155.py
netseasy/migrations/0003_auto_20210617_1027.py
netseasy/migrations/0004_auto_20210618_0806.py
netseasy/migrations/__init__.py
netseasy/models/__init__.py
netseasy/models/basedata.py
netseasy/models/payments.py
netseasy-0.1.1.dist-info/LICENSE
netseasy-0.1.1.dist-info/METADATA
netseasy-0.1.1.dist-info/WHEEL
netseasy-0.1.1.dist-info/top_level.txt
netseasy-0.1.1.dist-info/RECORD
