Metadata-Version: 2.1
Name: netseasy
Version: 0.1.1
Summary: netseasy - Django gateway for the payemnt solution Easy from Nets
Home-page: https://gitlab.com/norsktest/netseasy.git
Maintainer-email: itdrift@norsktest.no
License: UNKNOWN
Platform: UNKNOWN
Classifier: Development Status :: 3 - Alpha
Classifier: Intended Audience :: Developers
Classifier: Programming Language :: Python
Classifier: Programming Language :: Python :: 3.5
Classifier: Topic :: Software Development :: Libraries
